vmc_client/__init__.py
vmc_client/_async_client.py
vmc_client/_async_vmc.py
vmc_client/_constants.py
vmc_client/_sync_client.py
vmc_client/_sync_vmc.py
vmc_client/types/__init__.py
vmc_client/types/_base.py
vmc_client/types/_request.py
vmc_client/types/_types.py
vmc_client/types/audio/__init__.py
vmc_client/types/audio/create.py
vmc_client/types/audio/transcription.py
vmc_client/types/embedding/__init__.py
vmc_client/types/embedding/create.py
vmc_client/types/embedding/embedding.py
vmc_client/types/errors/__init__.py
vmc_client/types/errors/_base.py
vmc_client/types/errors/errors.py
vmc_client/types/errors/message.py
vmc_client/types/errors/status_code.py
vmc_client/types/generation/__init__.py
vmc_client/types/generation/generation.py
vmc_client/types/generation/generation_chunk.py
vmc_client/types/generation/generation_params.py
vmc_client/types/generation/message.py
vmc_client/types/generation/message_params.py
vmc_client/types/generation/named_tool_choice_param.py
vmc_client/types/generation/tokenize.py
vmc_client/types/generation/tool_choice_option_param.py
vmc_client/types/generation/tool_param.py
vmc_client/types/model_info.py
vmc_client/types/pricing.py
vmc_client/types/rerank/__init__.py
vmc_client/types/rerank/create.py
vmc_client/types/rerank/rerank.py
vmc_client/types/shared_params/function_definition.py
vmc_client/types/shared_params/function_parameters.py
vmc_client/types/shared_params/response_format.py
vmc_client/types/tokenize.py
vmc_client/vmc.py
vmc_client-0.1.0.dist-info/LICENSE
vmc_client-0.1.0.dist-info/METADATA
vmc_client-0.1.0.dist-info/WHEEL
vmc_client-0.1.0.dist-info/RECORD
